README.rst
setup.py
gethy/__init__.py
gethy/event.py
gethy/event_handle.py
gethy/http2protocol.py
gethy/state.py
gethy.egg-info/PKG-INFO
gethy.egg-info/SOURCES.txt
gethy.egg-info/dependency_links.txt
gethy.egg-info/requires.txt
gethy.egg-info/top_level.txt