Metadata-Version: 1.1
Name: gethy
Version: 0.0.0
Summary: An application level IO independent h2 library
Home-page: https://github.com/CreatCodeBuild/gethy
Author: CreatCodeBuild@github.com
Author-email: UNKNOWN
License: MIT
Keywords: HTTP/2
Platform: UNKNOWN
Classifier: Development Status :: 3 - Alpha
Classifier: Intended Audience :: Developers
Classifier: Topic :: Software Development :: Build Tools
Classifier: License :: OSI Approved :: MIT License
Classifier: Programming Language :: Python :: 3.5
Classifier: Programming Language :: Python :: 3.6
